validobj/__init__.py
validobj/custom.py
validobj/errors.py
validobj/py.typed
validobj/validation.py
validobj/tests/__init__.py
validobj/tests/conftest.py
validobj/tests/test_custom.py
validobj/tests/test_delayed_dataclasses.py
validobj/tests/test_errors.py
validobj/tests/test_type_syntax.py
validobj/tests/test_validation.py
validobj-1.6.dist-info/licenses/LICENSE
validobj-1.6.dist-info/WHEEL
validobj-1.6.dist-info/METADATA
validobj-1.6.dist-info/RECORD
