Metadata-Version: 2.4
Name: validobj
Version: 1.6
Summary: Validobj gives you valid objects
Home-page: https://github.com/Zaharid/validobj
Author: Zahari Kassabov
Author-email: zaharid@protonmail.com
Requires-Python: >=3.8
Classifier: License :: OSI Approved :: MIT License
License-File: LICENSE
Requires-Dist: sphinx ; extra == "doc"
Requires-Dist: ruamel.yaml ; extra == "doc"
Requires-Dist: sphinx_rtd_theme ; extra == "doc"
Requires-Dist: hypothesis ; extra == "test"
Requires-Dist: pytest ; extra == "test"
Requires-Dist: pytest-cov ; extra == "test"
Provides-Extra: doc
Provides-Extra: test
